README.rst
setup.py
HermesCache.egg-info/PKG-INFO
HermesCache.egg-info/SOURCES.txt
HermesCache.egg-info/dependency_links.txt
HermesCache.egg-info/requires.txt
HermesCache.egg-info/top_level.txt
hermes/__init__.py
hermes/backend/__init__.py
hermes/backend/inprocess.py
hermes/backend/memcached.py
hermes/backend/redis.py
hermes/test/__init__.py
hermes/test/abstract.py
hermes/test/facade.py
hermes/test/inprocess.py
hermes/test/memcached.py
hermes/test/redis.py