Metadata-Version: 2.1
Name: HermesCache
Version: 0.10.0
Summary: Python caching library with tag-based invalidation and dogpile effect prevention
Home-page: https://heptapod.host/saajns/hermes
Author: saaj
Author-email: mail@saaj.me
License: LGPL-2.1+
Project-URL: Source Code, https://heptapod.host/saajns/hermes
Project-URL: Documentation, https://hermescache.readthedocs.io/
Keywords: python cache tagging redis memcached
Platform: Any
Classifier: Topic :: Software Development :: Libraries
Classifier: Programming Language :: Python :: 3
Classifier: Programming Language :: Python :: 3 :: Only
Classifier: Programming Language :: Python :: 3.7
Classifier: Programming Language :: Python :: 3.8
Classifier: Programming Language :: Python :: 3.9
Classifier: Programming Language :: Python :: 3.10
Classifier: Programming Language :: Python :: Implementation :: CPython
Classifier: Programming Language :: Python :: Implementation :: PyPy
Classifier: Intended Audience :: Developers
Requires-Python: >= 3
Provides-Extra: redis
Provides-Extra: redis-ext
Provides-Extra: memcached
